<?xml version="1.0" encoding="utf-8" ?><dwsync><file name="BPdotsUnicase.otf" server="www.hernanjourdan.com//" local="3453213238" remote="12121863152" /><file name="BPdotsUnicaseBold.otf" server="www.hernanjourdan.com//" local="3453213238" remote="12121863152" /><file name="BPdotsUnicaseDiamond.otf" server="www.hernanjourdan.com//" local="3453213242" remote="12121863152" /><file name="BPdotsUnicaseDiamondBold.otf" server="www.hernanjourdan.com//" local="3453213242" remote="12121863152" /><file name="BPdotsUnicaseDiamondLight.otf" server="www.hernanjourdan.com//" local="3453213240" remote="12121863152" /><file name="BPdotsUnicaseLight.otf" server="www.hernanjourdan.com//" local="3453213236" remote="12121863152" /><file name="BPdotsUnicaseMinus.otf" server="www.hernanjourdan.com//" local="3453213244" remote="12121863152" /><file name="BPdotsUnicaseMinusBold.otf" server="www.hernanjourdan.com//" local="3453213244" remote="12121863152" /><file name="BPdotsUnicasePlus.otf" server="www.hernanjourdan.com//" local="3453213242" remote="12121863152" /><file name="BPdotsUnicasePlusBold.otf" server="www.hernanjourdan.com//" local="3453213244" remote="12121863152" /><file name="BPdotsUnicaseSquare.otf" server="www.hernanjourdan.com//" local="3453213240" remote="12121863152" /><file name="BPdotsUnicaseSquareBold.otf" server="www.hernanjourdan.com//" local="3453213240" remote="12121863152" /><file name="BPdotsUnicaseSquareLight.otf" server="www.hernanjourdan.com//" local="3453213240" remote="12121863152" /><file name="BPdotsUnicaseVertical.otf" server="www.hernanjourdan.com//" local="3453213246" remote="12121863152" /><file name="BPdotsUnicaseVerticalBold.otf" server="www.hernanjourdan.com//" local="3453213246" remote="12121863152" /><file name="Creative Commons Attribution-No Derivative Works.txt" server="www.hernanjourdan.com//" local="3518875268" remote="12121863152" /><file name="BPdotsUnicase.otf" server="www.hernanjourdan.com//public_html/hernanjourdan.com/" local="3453213238" remote="12121863512" /><file name="BPdotsUnicaseBold.otf" server="www.hernanjourdan.com//public_html/hernanjourdan.com/" local="3453213238" remote="12121863512" /><file name="BPdotsUnicaseDiamond.otf" server="www.hernanjourdan.com//public_html/hernanjourdan.com/" local="3453213242" remote="12121863512" /><file name="BPdotsUnicaseDiamondBold.otf" server="www.hernanjourdan.com//public_html/hernanjourdan.com/" local="3453213242" remote="12121863512" /><file name="BPdotsUnicaseDiamondLight.otf" server="www.hernanjourdan.com//public_html/hernanjourdan.com/" local="3453213240" remote="12121863512" /><file name="BPdotsUnicaseLight.otf" server="www.hernanjourdan.com//public_html/hernanjourdan.com/" local="3453213236" remote="12121863512" /><file name="BPdotsUnicaseMinus.otf" server="www.hernanjourdan.com//public_html/hernanjourdan.com/" local="3453213244" remote="12121863512" /><file name="BPdotsUnicaseMinusBold.otf" server="www.hernanjourdan.com//public_html/hernanjourdan.com/" local="3453213244" remote="12121863512" /><file name="BPdotsUnicasePlus.otf" server="www.hernanjourdan.com//public_html/hernanjourdan.com/" local="3453213242" remote="12121863512" /><file name="BPdotsUnicasePlusBold.otf" server="www.hernanjourdan.com//public_html/hernanjourdan.com/" local="3453213244" remote="12121863512" /><file name="BPdotsUnicaseSquare.otf" server="www.hernanjourdan.com//public_html/hernanjourdan.com/" local="3453213240" remote="12121863512" /><file name="BPdotsUnicaseSquareBold.otf" server="www.hernanjourdan.com//public_html/hernanjourdan.com/" local="3453213240" remote="12121863512" /><file name="BPdotsUnicaseSquareLight.otf" server="www.hernanjourdan.com//public_html/hernanjourdan.com/" local="3453213240" remote="12121863512" /><file name="BPdotsUnicaseVertical.otf" server="www.hernanjourdan.com//public_html/hernanjourdan.com/" local="3453213246" remote="12121863512" /><file name="BPdotsUnicaseVerticalBold.otf" server="www.hernanjourdan.com//public_html/hernanjourdan.com/" local="3453213246" remote="12121863512" /><file name="Creative Commons Attribution-No Derivative Works.txt" server="www.hernanjourdan.com//public_html/hernanjourdan.com/" local="3518875268" remote="12121863512" /><file name="BPdotsUnicase.otf" server="www.hernanjourdan.com//public_html/" local="3453213238" remote="12121866632" /><file name="BPdotsUnicaseBold.otf" server="www.hernanjourdan.com//public_html/" local="3453213238" remote="12121866632" /><file name="BPdotsUnicaseDiamond.otf" server="www.hernanjourdan.com//public_html/" local="3453213242" remote="12121866632" /><file name="BPdotsUnicaseDiamondBold.otf" server="www.hernanjourdan.com//public_html/" local="3453213242" remote="12121866632" /><file name="BPdotsUnicaseDiamondLight.otf" server="www.hernanjourdan.com//public_html/" local="3453213240" remote="12121866632" /><file name="BPdotsUnicaseLight.otf" server="www.hernanjourdan.com//public_html/" local="3453213236" remote="12121866632" /><file name="BPdotsUnicaseMinus.otf" server="www.hernanjourdan.com//public_html/" local="3453213244" remote="12121866632" /><file name="BPdotsUnicaseMinusBold.otf" server="www.hernanjourdan.com//public_html/" local="3453213244" remote="12121866632" /><file name="BPdotsUnicasePlus.otf" server="www.hernanjourdan.com//public_html/" local="3453213242" remote="12121866632" /><file name="BPdotsUnicasePlusBold.otf" server="www.hernanjourdan.com//public_html/" local="3453213244" remote="12121866632" /><file name="BPdotsUnicaseSquare.otf" server="www.hernanjourdan.com//public_html/" local="3453213240" remote="12121866632" /><file name="BPdotsUnicaseSquareBold.otf" server="www.hernanjourdan.com//public_html/" local="3453213240" remote="12121866632" /><file name="BPdotsUnicaseSquareLight.otf" server="www.hernanjourdan.com//public_html/" local="3453213240" remote="12121866632" /><file name="BPdotsUnicaseVertical.otf" server="www.hernanjourdan.com//public_html/" local="3453213246" remote="12121866632" /><file name="BPdotsUnicaseVerticalBold.otf" server="www.hernanjourdan.com//public_html/" local="3453213246" remote="12121866632" /><file name="Creative Commons Attribution-No Derivative Works.txt" server="www.hernanjourdan.com//public_html/" local="3518875268" remote="12121866632" /></dwsync>