<?xml version="1.0" encoding="utf-8" ?><dwsync><file name="Existence-Light.otf" server="www.hernanjourdan.com//" local="3453213758" remote="12121863152" /><file name="Existence-StencilLight.otf" server="www.hernanjourdan.com//" local="3453213760" remote="12121863152" /><file name="Existence-UnicaseLight.otf" server="www.hernanjourdan.com//" local="3453213758" remote="12121863152" /><file name="Yeah Noah License.txt" server="www.hernanjourdan.com//" local="3518875358" remote="12121863152" /><file name="Existence-Light.otf" server="www.hernanjourdan.com//public_html/hernanjourdan.com/" local="3453213758" remote="12121863512" /><file name="Existence-StencilLight.otf" server="www.hernanjourdan.com//public_html/hernanjourdan.com/" local="3453213760" remote="12121863512" /><file name="Existence-UnicaseLight.otf" server="www.hernanjourdan.com//public_html/hernanjourdan.com/" local="3453213758" remote="12121863512" /><file name="Yeah Noah License.txt" server="www.hernanjourdan.com//public_html/hernanjourdan.com/" local="3518875358" remote="12121863512" /><file name="Existence-Light.otf" server="www.hernanjourdan.com//public_html/" local="3453213758" remote="12121866632" /><file name="Existence-StencilLight.otf" server="www.hernanjourdan.com//public_html/" local="3453213760" remote="12121866632" /><file name="Existence-UnicaseLight.otf" server="www.hernanjourdan.com//public_html/" local="3453213758" remote="12121866632" /><file name="Yeah Noah License.txt" server="www.hernanjourdan.com//public_html/" local="3518875358" remote="12121866632" /></dwsync>